README.md
setup.cfg
setup.py
phitools/SDFToData.py
phitools/__init__.py
phitools/addDataToSDF.py
phitools/addInchi.py
phitools/addSDFToData.py
phitools/extractData.py
phitools/findDuplicates.py
phitools/getSDF.py
phitools/getStructure.py
phitools/join.py
phitools/moleculeHelper.py
phitools/pivot.py
phitools/randomSplitSDF.py
phitools/similarity.py
phitools/uniqueStructures.py
phitools/viewSDF.py
phitools.egg-info/PKG-INFO
phitools.egg-info/SOURCES.txt
phitools.egg-info/dependency_links.txt
phitools.egg-info/top_level.txt