Metadata-Version: 1.1
Name: phitools
Version: 0.3
Summary: Collection of simple tools used for manipulating series of chemical compounds
Home-page: https://github.com/bet-gregori/phitools
Author: Manuel Pastor and Elisabet Gregori
Author-email: manuel.pastor@upf.edu
License: GNU GPLv3
Download-URL: https://github.com/bet-gregori/phitools/archive/v0.3.tar.gz
Platform: UNKNOWN
